dictlib/__init__.py
dictlib-1.1.5.dist-info/LICENSE.txt
dictlib-1.1.5.dist-info/METADATA
dictlib-1.1.5.dist-info/WHEEL
dictlib-1.1.5.dist-info/top_level.txt
dictlib-1.1.5.dist-info/RECORD
