Metadata-Version: 2.1
Name: dictlib
Version: 1.1.5
Summary: Dictionary Library including good deep merge and dictionary as objects
Home-page: https://github.com/srevenant/dictlib
Author: Brandon Gillespie
Author-email: bjg-pypi@cold.org
License: UNKNOWN
Keywords: dict,union,object,dig,dug
Platform: UNKNOWN
Classifier: Programming Language :: Python :: 3
Classifier: License :: OSI Approved :: GNU Affero General Public License v3
Classifier: Operating System :: OS Independent
